MANIFEST.in
README.md
setup.py
procell/__init__.py
procell/about2.ui
procell/cell.py
procell/cells_population.py
procell/create_stack.py
procell/estimator.py
procell/fitness.py
procell/gui.py
procell/mainwindow2.ui
procell/new_projects_bag.py
procell/preferences.ui
procell/procell.qss
procell/procell_core.py
procell/project.py
procell/resources.py
procell/resources3.py
procell/simulator.py
procell/test.py
procell.egg-info/PKG-INFO
procell.egg-info/SOURCES.txt
procell.egg-info/dependency_links.txt
procell.egg-info/requires.txt
procell.egg-info/top_level.txt
procell/gui_material/addnew.png
procell/gui_material/cancel.png
procell/gui_material/cells.png
procell/gui_material/petri_dish.png
procell/gui_material/play.png
procell/gui_material/procell_logo.png
procell/gui_material/procell_logo2.png
procell/gui_material/procell_logo_small.png
procell/gui_material/stop.png
procell/gui_material/triangolo.png
procell/gui_material/validate.png