Metadata-Version: 2.1
Name: procell
Version: 1.7.2
Summary: ProCell - cell proliferation framework
Home-page: https://github.com/aresio/ProCell
Author: Marco S. Nobile
Author-email: m.s.nobile@tue.nl
License: UNKNOWN
Platform: UNKNOWN
Classifier: Programming Language :: Python :: 3
Classifier: License :: OSI Approved :: GNU General Public License v2 (GPLv2)
Classifier: Operating System :: OS Independent
